Metadata-Version: 2.1
Name: oneNeuron-pypi-idur69
Version: 0.0.2
Summary: It's an implimentation of Perceptron
Home-page: https://github.com/idur69/oneNeuron_pypi
Author: idur69
Author-email: shaikidurbasha469@gmail.com
License: UNKNOWN
Project-URL: Bug Tracker, https://github.com/idur69/oneNeuron_pypi/issues
Platform: UNKNOWN
Classifier: Programming Language :: Python :: 3
Classifier: License :: OSI Approved :: MIT License
Classifier: Operating System :: OS Independent
Requires-Python: >=3.6
License-File: LICENSE
Requires-Dist: numpy
Requires-Dist: tqdm
